hoernchen/__init__.py
hoernchen/py.typed
hoernchen/store.py
hoernchen-0.7.1.dist-info/licenses/LICENSE
hoernchen-0.7.1.dist-info/METADATA
hoernchen-0.7.1.dist-info/WHEEL
hoernchen-0.7.1.dist-info/top_level.txt
hoernchen-0.7.1.dist-info/RECORD
