Metadata-Version: 2.4
Name: hoernchen
Version: 0.7.1
Summary: sqlite3 wrapper based on dataclasses
Author-email: Simon Haendeler <syntaar@gmail.com>
Requires-Python: >=3.7
License-File: LICENSE
Dynamic: license-file
